sefile/__init__.py
sefile/_create_project.py
sefile/_custom_query.py
sefile/_decorator.py
sefile/app.py
sefile/callbacks.py
sefile/command.py
sefile/config.py
sefile/controllers.py
sefile/editor.py
sefile/exception.py
sefile/logging.py
new_sefile-0.0.17.dist-info/LICENSE.md
new_sefile-0.0.17.dist-info/METADATA
new_sefile-0.0.17.dist-info/WHEEL
new_sefile-0.0.17.dist-info/entry_points.txt
new_sefile-0.0.17.dist-info/top_level.txt
new_sefile-0.0.17.dist-info/RECORD
