Metadata-Version: 2.1
Name: new-sefile
Version: 0.0.17
Summary: CLI tool for searching file in your PC
Author-email: Faisal Ramadhan <faisalramadhan1299@gmail.com>
Project-URL: Homepage, https://github.com/Kolong-Meja/search-cli
Project-URL: Bug Tracker, https://github.com/Kolong-Meja/search-cli/issues
Classifier: Programming Language :: Python :: 3.10
Classifier: License :: OSI Approved :: GNU General Public License v3 (GPLv3)
Classifier: Operating System :: POSIX :: Linux
Requires-Python: >=3.10
License-File: LICENSE.md
Requires-Dist: npyscreen ==4.10.5
Requires-Dist: ascii-magic ==2.3.0
Requires-Dist: typer ==0.9.0
Requires-Dist: colorama ==0.4.6
Requires-Dist: click ==8.1.7
Requires-Dist: Pillow ==10.0.0
Requires-Dist: rich ==13.5.2
Requires-Dist: termcolor ==2.3.0
Requires-Dist: python-dotenv ==1.0.0
Requires-Dist: art ==6.1
Requires-Dist: bullet ==2.2.0
